{
  "indexes": [
    {
      "collectionGroup": "transactions",
      "queryScope": "COLLECTION",
      "fields": [
        {
          "fieldPath": "userId",
          "order": "ASCENDING"
        },
        {
          "fieldPath": "accountId",
          "order": "ASCENDING"
        },
        {
          "fieldPath": "transactionDate",
          "order": "DESCENDING"
        }
      ]
    },
    {
      "collectionGroup": "transactions",
      "queryScope": "COLLECTION",
      "fields": [
        {
          "fieldPath": "userId",
          "order": "ASCENDING"
        },
        {
          "fieldPath": "subAccountId",
          "order": "ASCENDING"
        },
        {
          "fieldPath": "transactionDate",
          "order": "DESCENDING"
        }
      ]
    },
    {
      "collectionGroup": "transactions",
      "queryScope": "COLLECTION",
      "fields": [
        {
          "fieldPath": "userId",
          "order": "ASCENDING"
        },
        {
          "fieldPath": "transactionType",
          "order": "ASCENDING"
        },
        {
          "fieldPath": "transactionDate",
          "order": "DESCENDING"
        }
      ]
    },
    {
      "collectionGroup": "subAccounts",
      "queryScope": "COLLECTION",
      "fields": [
        {
          "fieldPath": "userId",
          "order": "ASCENDING"
        },
        {
          "fieldPath": "accountId",
          "order": "ASCENDING"
        },
        {
          "fieldPath": "name",
          "order": "ASCENDING"
        }
      ]
    },
    {
      "collectionGroup": "subAccounts",
      "queryScope": "COLLECTION",
      "fields": [
        {
          "fieldPath": "userId",
          "order": "ASCENDING"
        },
        {
          "fieldPath": "accountId",
          "order": "ASCENDING"
        },
        {
          "fieldPath": "isFavorite",
          "order": "ASCENDING"
        }
      ]
    },
    {
      "collectionGroup": "accounts",
      "queryScope": "COLLECTION",
      "fields": [
        {
          "fieldPath": "userId",
          "order": "ASCENDING"
        },
        {
          "fieldPath": "accountType",
          "order": "ASCENDING"
        },
        {
          "fieldPath": "createdAt",
          "order": "DESCENDING"
        }
      ]
    },
    {
      "collectionGroup": "accounts",
      "queryScope": "COLLECTION",
      "fields": [
        {
          "fieldPath": "userId",
          "order": "ASCENDING"
        },
        {
          "fieldPath": "isFavorite",
          "order": "ASCENDING"
        },
        {
          "fieldPath": "createdAt",
          "order": "DESCENDING"
        }
      ]
    },
    {
      "collectionGroup": "favorites",
      "queryScope": "COLLECTION",
      "fields": [
        {
          "fieldPath": "userId",
          "order": "ASCENDING"
        },
        {
          "fieldPath": "createdAt",
          "order": "DESCENDING"
        }
      ]
    }
  ],
  "fieldOverrides": []
}

